micantis/__init__.py
micantis/api_wrapper.py
micantis/utils.py
micantis-0.1.13.dist-info/licenses/LICENSE
micantis-0.1.13.dist-info/METADATA
micantis-0.1.13.dist-info/WHEEL
micantis-0.1.13.dist-info/top_level.txt
micantis-0.1.13.dist-info/RECORD
