Metadata-Version: 2.4
Name: micantis
Version: 0.1.13
Summary: Package to simplify Micantis API usage
Author-email: Mykela DeLuca <mykela.deluca@micantis.io>
License: MIT
Requires-Python: >=3.7
License-File: LICENSE
Requires-Dist: requests
Requires-Dist: pandas
Requires-Dist: msal
Requires-Dist: azure-identity
Dynamic: license-file
